Workbook

Sheet Акции
A1: Дата | B1: Бренд | C1: Артикул | D1: Скидка, % | E1: Сегмент | F1: 80 | G1: шт
A2: 45292 | B2: Astro Venture | C2: 63111 | D2: 0.2 | E2: =VLOOKUP(C2,Лист1!H:K,4,0) -> СТОК-ВИАТ | F2: =VLOOKUP(C2,Лист1!H:L,5,0) -> 416.1 | G2: =IFERROR(VLOOKUP(CONCATENATE(C2,A2),Лист1!D:E,2,0),0) -> 0
A3: 45292 | B3: Astro Venture | C3: 63112 | D3: 0.2 | E3: =VLOOKUP(C3,Лист1!H:K,4,0) -> СТОК-ВИАТ | F3: =VLOOKUP(C3,Лист1!H:L,5,0) -> 499.44 | G3: =IFERROR(VLOOKUP(CONCATENATE(C3,A3),Лист1!D:E,2,0),0) -> 0
A4: 45292 | B4: Astro Venture | C4: 63113 | D4: 0.2 | E4: =VLOOKUP(C4,Лист1!H:K,4,0) -> ВИАТ | F4: =VLOOKUP(C4,Лист1!H:L,5,0) -> 832.8 | G4: =IFERROR(VLOOKUP(CONCATENATE(C4,A4),Лист1!D:E,2,0),0) -> 0
A5: 45292 | B5: Astro Venture | C5: 63114 | D5: 0.2 | E5: =VLOOKUP(C5,Лист1!H:K,4,0) -> СТОК-ВИАТ | F5: =VLOOKUP(C5,Лист1!H:L,5,0) -> 1332.78 | G5: =IFERROR(VLOOKUP(CONCATENATE(C5,A5),Лист1!D:E,2,0),0) -> 0
A6: 45292 | B6: Astro Venture | C6: 63115 | D6: 0.2 | E6: =VLOOKUP(C6,Лист1!H:K,4,0) -> СТОК-ВИАТ | F6: =VLOOKUP(C6,Лист1!H:L,5,0) -> 1666.14 | G6: =IFERROR(VLOOKUP(CONCATENATE(C6,A6),Лист1!D:E,2,0),0) -> 0
A7: 45292 | B7: Astro Venture | C7: 63118 | D7: 0.2 | E7: =VLOOKUP(C7,Лист1!H:K,4,0) -> СТОК-ВИАТ | F7: =VLOOKUP(C7,Лист1!H:L,5,0) -> 1943.88 | G7: =IFERROR(VLOOKUP(CONCATENATE(C7,A7),Лист1!D:E,2,0),0) -> 0
A8: 45292 | B8: Astro Venture | C8: 63140 | D8: 0.2 | E8: =VLOOKUP(C8,Лист1!H:K,4,0) -> СТОК-ВИАТ | F8: =VLOOKUP(C8,Лист1!H:L,5,0) -> 1054.98 | G8: =IFERROR(VLOOKUP(CONCATENATE(C8,A8),Лист1!D:E,2,0),0) -> 0
A9: 45292 | B9: Astro Venture | C9: 63141 | D9: 0.2 | E9: =VLOOKUP(C9,Лист1!H:K,4,0) -> СТОК-ВИАТ | F9: =VLOOKUP(C9,Лист1!H:L,5,0) -> 721.68 | G9: =IFERROR(VLOOKUP(CONCATENATE(C9,A9),Лист1!D:E,2,0),0) -> 0
A10: 45292 | B10: Astro Venture | C10: 63142 | D10: 0.25 | E10: =VLOOKUP(C10,Лист1!H:K,4,0) -> СТОК-ВИАТ | F10: =VLOOKUP(C10,Лист1!H:L,5,0) -> 1832.76 | G10: =IFERROR(VLOOKUP(CONCATENATE(C10,A10),Лист1!D:E,2,0),0) -> 0
A11: 45292 | B11: Astro Venture | C11: 63146 | D11: 0.2 | E11: =VLOOKUP(C11,Лист1!H:K,4,0) -> СТОК-ВИАТ | F11: =VLOOKUP(C11,Лист1!H:L,5,0) -> 721.68 | G11: =IFERROR(VLOOKUP(CONCATENATE(C11,A11),Лист1!D:E,2,0),0) -> 0
A12: 45292 | B12: Astro Venture | C12: 63153 | D12: 0.2 | E12: =VLOOKUP(C12,Лист1!H:K,4,0) -> СТОК-ВИАТ | F12: =VLOOKUP(C12,Лист1!H:L,5,0) -> 832.8 | G12: =IFERROR(VLOOKUP(CONCATENATE(C12,A12),Лист1!D:E,2,0),0) -> 0
A13: 45292 | B13: Astro Venture | C13: 63154 | D13: 0.2 | E13: =VLOOKUP(C13,Лист1!H:K,4,0) -> СТОК-ВИАТ | F13: =VLOOKUP(C13,Лист1!H:L,5,0) -> 555 | G13: =IFERROR(VLOOKUP(CONCATENATE(C13,A13),Лист1!D:E,2,0),0) -> 0
... A53: 45292 | B53: Chap Mei | C53: 545314 | D53: 0.2 | E53: =VLOOKUP(C53,Лист1!H:K,4,0) -> ВИАТ | F53: =VLOOKUP(C53,Лист1!H:L,5,0) -> 666.12 | G53: =IFERROR(VLOOKUP(CONCATENATE(C53,A53),Лист1!D:E,2,0),0) -> 0
A54: 45292 | B54: Chap Mei | C54: 545008-1 | D54: 0.2 | E54: =VLOOKUP(C54,Лист1!H:K,4,0) -> СТОК-ВИАТ | F54: =VLOOKUP(C54,Лист1!H:L,5,0) -> 304.98 | G54: =IFERROR(VLOOKUP(CONCATENATE(C54,A54),Лист1!D:E,2,0),0) -> 0
A55: 45292 | B55: Chap Mei | C55: 545300-1 | D55: 0.2 | E55: =VLOOKUP(C55,Лист1!H:K,4,0) -> V | F55: =VLOOKUP(C55,Лист1!H:L,5,0) -> 277.2 | G55: =IFERROR(VLOOKUP(CONCATENATE(C55,A55),Лист1!D:E,2,0),0) -> 0
A56: 45292 | B56: Crystal Art | C56: CAFGR-MCU002 | D56: 0.2 | E56: =VLOOKUP(C56,Лист1!H:K,4,0) -> V | F56: =VLOOKUP(C56,Лист1!H:L,5,0) -> 110.58 | G56: =IFERROR(VLOOKUP(CONCATENATE(C56,A56),Лист1!D:E,2,0),0) -> 0
A57: 45292 | B57: Crystal Art | C57: CAFGR-MCU003 | D57: 0.2 | E57: =VLOOKUP(C57,Лист1!H:K,4,0) -> V | F57: =VLOOKUP(C57,Лист1!H:L,5,0) -> 110.58 | G57: =IFERROR(VLOOKUP(CONCATENATE(C57,A57),Лист1!D:E,2,0),0) -> 0
A58: 45292 | B58: Crystal Art | C58: CAFGR-MCU004 | D58: 0.2 | E58: =VLOOKUP(C58,Лист1!H:K,4,0) -> V | F58: =VLOOKUP(C58,Лист1!H:L,5,0) -> 110.58 | G58: =IFERROR(VLOOKUP(CONCATENATE(C58,A58),Лист1!D:E,2,0),0) -> 0
A59: 45292 | B59: Crystal Art | C59: CAFGR-MCU005 | D59: 0.2 | E59: =VLOOKUP(C59,Лист1!H:K,4,0) -> V | F59: =VLOOKUP(C59,Лист1!H:L,5,0) -> 110.58 | G59: =IFERROR(VLOOKUP(CONCATENATE(C59,A59),Лист1!D:E,2,0),0) -> 0
A60: 45292 | B60: Crystal Art | C60: CAFGR-MCU006 | D60: 0.2 | E60: =VLOOKUP(C60,Лист1!H:K,4,0) -> V | F60: =VLOOKUP(C60,Лист1!H:L,5,0) -> 110.58 | G60: =IFERROR(VLOOKUP(CONCATENATE(C60,A60),Лист1!D:E,2,0),0) -> 0
A61: 45292 | B61: Crystal Art | C61: CAFGR-MCU007 | D61: 0.2 | E61: =VLOOKUP(C61,Лист1!H:K,4,0) -> V | F61: =VLOOKUP(C61,Лист1!H:L,5,0) -> 110.58 | G61: =IFERROR(VLOOKUP(CONCATENATE(C61,A61),Лист1!D:E,2,0),0) -> 0
A62: 45292 | B62: Crystal Art | C62: CAFGR-SWS001 | D62: 0.2 | E62: =VLOOKUP(C62,Лист1!H:K,4,0) -> V | F62: =VLOOKUP(C62,Лист1!H:L,5,0) -> 110.58 | G62: =IFERROR(VLOOKUP(CONCATENATE(C62,A62),Лист1!D:E,2,0),0) -> 0
A63: 45292 | B63: Crystal Art | C63: CAFGR-SWS002 | D63: 0.2 | E63: =VLOOKUP(C63,Лист1!H:K,4,0) -> V | F63: =VLOOKUP(C63,Лист1!H:L,5,0) -> 110.58 | G63: =IFERROR(VLOOKUP(CONCATENATE(C63,A63),Лист1!D:E,2,0),0) -> 0
A64: 45292 | B64: Crystal Art | C64: CAFGR-SWS004 | D64: 0.2 | E64: =VLOOKUP(C64,Лист1!H:K,4,0) -> V | F64: =VLOOKUP(C64,Лист1!H:L,5,0) -> 110.58 | G64: =IFERROR(VLOOKUP(CONCATENATE(C64,A64),Лист1!D:E,2,0),0) -> 0
A65: 45292 | B65: Crystal Art | C65: CAFGR-SWS005 | D65: 0.2 | E65: =VLOOKUP(C65,Лист1!H:K,4,0) -> V | F65: =VLOOKUP(C65,Лист1!H:L,5,0) -> 110.58 | G65: =IFERROR(VLOOKUP(CONCATENATE(C65,A65),Лист1!D:E,2,0),0) -> 0
... A91: 45292 | B91: Cubic Fun | C91: T4039h | D91: 0.2 | E91: =VLOOKUP(C91,Лист1!H:K,4,0) -> В | F91: =VLOOKUP(C91,Лист1!H:L,5,0) -> 555 | G91: =IFERROR(VLOOKUP(CONCATENATE(C91,A91),Лист1!D:E,2,0),0) -> 0
A92: 45292 | B92: Dino Valley | C92: 542015 | D92: 0.2 | E92: =VLOOKUP(C92,Лист1!H:K,4,0) -> V | F92: =VLOOKUP(C92,Лист1!H:L,5,0) -> 360.54 | G92: =IFERROR(VLOOKUP(CONCATENATE(C92,A92),Лист1!D:E,2,0),0) -> 0
A93: 45292 | B93: Dino Valley | C93: 542017 | D93: 0.2 | E93: =VLOOKUP(C93,Лист1!H:K,4,0) -> V | F93: =VLOOKUP(C93,Лист1!H:L,5,0) -> 666.12 | G93: =IFERROR(VLOOKUP(CONCATENATE(C93,A93),Лист1!D:E,2,0),0) -> 0
A94: 45292 | B94: Dino Valley | C94: 542028 | D94: 0.2 | E94: =VLOOKUP(C94,Лист1!H:K,4,0) -> СТОК-ВИАТ | F94: =VLOOKUP(C94,Лист1!H:L,5,0) -> 332.76 | G94: =IFERROR(VLOOKUP(CONCATENATE(C94,A94),Лист1!D:E,2,0),0) -> 0
A95: 45292 | B95: Dino Valley | C95: 542051 | D95: 0.3 | E95: =VLOOKUP(C95,Лист1!H:K,4,0) -> СТОК-ВИАТ | F95: =VLOOKUP(C95,Лист1!H:L,5,0) -> 1110.54 | G95: =IFERROR(VLOOKUP(CONCATENATE(C95,A95),Лист1!D:E,2,0),0) -> 0
A96: 45292 | B96: Dino Valley | C96: 542076 | D96: 0.3 | E96: =VLOOKUP(C96,Лист1!H:K,4,0) -> СТОК-ВИАТ | F96: =VLOOKUP(C96,Лист1!H:L,5,0) -> 832.8 | G96: =IFERROR(VLOOKUP(CONCATENATE(C96,A96),Лист1!D:E,2,0),0) -> 0
A97: 45292 | B97: Dino Valley | C97: 542087 | D97: 0.2 | E97: =VLOOKUP(C97,Лист1!H:K,4,0) -> СТОК-ВИАТ | F97: =VLOOKUP(C97,Лист1!H:L,5,0) -> 499.44 | G97: =IFERROR(VLOOKUP(CONCATENATE(C97,A97),Лист1!D:E,2,0),0) -> 0
A98: 45292 | B98: Dino Valley | C98: 542090 | D98: 0.2 | E98: =VLOOKUP(C98,Лист1!H:K,4,0) -> СТОК-ВИАТ | F98: =VLOOKUP(C98,Лист1!H:L,5,0) -> 666.12 | G98: =IFERROR(VLOOKUP(CONCATENATE(C98,A98),Лист1!D:E,2,0),0) -> 0
A99: 45292 | B99: Dino Valley | C99: 542120 | D99: 0.2 | E99: =VLOOKUP(C99,Лист1!H:K,4,0) -> СТОК-ВИАТ | F99: =VLOOKUP(C99,Лист1!H:L,5,0) -> 666.12 | G99: =IFERROR(VLOOKUP(CONCATENATE(C99,A99),Лист1!D:E,2,0),0) -> 0
A100: 45292 | B100: Dino Valley | C100: 542015-1 | D100: 0.2 | E100: =VLOOKUP(C100,Лист1!H:K,4,0) -> V | F100: =VLOOKUP(C100,Лист1!H:L,5,0) -> 360.54 | G100: =IFERROR(VLOOKUP(CONCATENATE(C100,A100),Лист1!D:E,2,0),0) -> 0
A101: 45292 | B101: Dino Valley | C101: 542083-2 | D101: 0.2 | E101: =VLOOKUP(C101,Лист1!H:K,4,0) -> СТОК-ВИАТ | F101: =VLOOKUP(C101,Лист1!H:L,5,0) -> 388.32 | G101: =IFERROR(VLOOKUP(CONCATENATE(C101,A101),Лист1!D:E,2,0),0) -> 0
A102: 45292 | B102: Djeco | C102: DD03485 | D102: 0.2 | E102: =VLOOKUP(C102,Лист1!H:K,4,0) -> СТОК-ВИАТ | F102: =VLOOKUP(C102,Лист1!H:L,5,0) -> 304.98 | G102: =IFERROR(VLOOKUP(CONCATENATE(C102,A102),Лист1!D:E,2,0),0) -> 0
A103: 45292 | B103: Djeco | C103: DD04670 | D103: 0.2 | E103: =VLOOKUP(C103,Лист1!H:K,4,0) -> V | F103: =VLOOKUP(C103,Лист1!H:L,5,0) -> 555 | G103: =IFERROR(VLOOKUP(CONCATENATE(C103,A103),Лист1!D:E,2,0),0) -> 0
A104: 45292 | B104: Djeco | C104: DD04671 | D104: 0.2 | E104: =VLOOKUP(C104,Лист1!H:K,4,0) -> V | F104: =VLOOKUP(C104,Лист1!H:L,5,0) -> 555 | G104: =IFERROR(VLOOKUP(CONCATENATE(C104,A104),Лист1!D:E,2,0),0) -> 0
A105: 45292 | B105: Djeco | C105: DD04673 | D105: 0.2 | E105: =VLOOKUP(C105,Лист1!H:K,4,0) -> V | F105: =VLOOKUP(C105,Лист1!H:L,5,0) -> 555 | G105: =IFERROR(VLOOKUP(CONCATENATE(C105,A105),Лист1!D:E,2,0),0) -> 0
A106: 45292 | B106: Djeco | C106: DD04681 | D106: 0.2 | E106: =VLOOKUP(C106,Лист1!H:K,4,0) -> V | F106: =VLOOKUP(C106,Лист1!H:L,5,0) -> 555 | G106: =IFERROR(VLOOKUP(CONCATENATE(C106,A106),Лист1!D:E,2,0),0) -> 0
A107: 45292 | B107: Djeco | C107: DD04717 | D107: 0.2 | E107: =VLOOKUP(C107,Лист1!H:K,4,0) -> В | F107: =VLOOKUP(C107,Лист1!H:L,5,0) -> 304.98 | G107: =IFERROR(VLOOKUP(CONCATENATE(C107,A107),Лист1!D:E,2,0),0) -> 0
A108: 45292 | B108: Djeco | C108: DJ00010 | D108: 0.2 | E108: =VLOOKUP(C108,Лист1!H:K,4,0) -> ВИАТ | F108: =VLOOKUP(C108,Лист1!H:L,5,0) -> 443.88 | G108: =IFERROR(VLOOKUP(CONCATENATE(C108,A108),Лист1!D:E,2,0),0) -> 0
A109: 45292 | B109: Djeco | C109: DJ00014 | D109: 0.2 | E109: =VLOOKUP(C109,Лист1!H:K,4,0) -> ВИАТ | F109: =VLOOKUP(C109,Лист1!H:L,5,0) -> 443.88 | G109: =IFERROR(VLOOKUP(CONCATENATE(C109,A109),Лист1!D:E,2,0),0) -> 0
A110: 45292 | B110: Djeco | C110: DJ00016 | D110: 0.2 | E110: =VLOOKUP(C110,Лист1!H:K,4,0) -> ВИАТ | F110: =VLOOKUP(C110,Лист1!H:L,5,0) -> 443.88 | G110: =IFERROR(VLOOKUP(CONCATENATE(C110,A110),Лист1!D:E,2,0),0) -> 0
A111: 45292 | B111: Djeco | C111: DJ00017 | D111: 0.2 | E111: =VLOOKUP(C111,Лист1!H:K,4,0) -> ВИАТ | F111: =VLOOKUP(C111,Лист1!H:L,5,0) -> 443.88 | G111: =IFERROR(VLOOKUP(CONCATENATE(C111,A111),Лист1!D:E,2,0),0) -> 0
... A264: 45292 | B264: Five Stars | C264: 460-12 | D264: 0.2 | E264: =VLOOKUP(C264,Лист1!H:K,4,0) -> V | F264: =VLOOKUP(C264,Лист1!H:L,5,0) -> 666.12 | G264: =IFERROR(VLOOKUP(CONCATENATE(C264,A264),Лист1!D:E,2,0),0) -> 0
A265: 45292 | B265: GraviTrax | C265: 26079 | D265: 0.2 | E265: =VLOOKUP(C265,Лист1!H:K,4,0) -> С | F265: =VLOOKUP(C265,Лист1!H:L,5,0) -> 388.32 | G265: =IFERROR(VLOOKUP(CONCATENATE(C265,A265),Лист1!D:E,2,0),0) -> 0
A266: 45292 | B266: GraviTrax | C266: 26080 | D266: 0.25 | E266: =VLOOKUP(C266,Лист1!H:K,4,0) -> В | F266: =VLOOKUP(C266,Лист1!H:L,5,0) -> 777.24 | G266: =IFERROR(VLOOKUP(CONCATENATE(C266,A266),Лист1!D:E,2,0),0) -> 0
A267: 45292 | B267: GraviTrax | C267: 26099 | D267: 0.15 | E267: =VLOOKUP(C267,Лист1!H:K,4,0) -> А | F267: =VLOOKUP(C267,Лист1!H:L,5,0) -> 2221.68 | G267: =IFERROR(VLOOKUP(CONCATENATE(C267,A267),Лист1!D:E,2,0),0) -> 0
A268: 45292 | B268: GraviTrax | C268: 26816 | D268: 0.25 | E268: =VLOOKUP(C268,Лист1!H:K,4,0) -> С | F268: =VLOOKUP(C268,Лист1!H:L,5,0) -> 1054.98 | G268: =IFERROR(VLOOKUP(CONCATENATE(C268,A268),Лист1!D:E,2,0),0) -> 0
A269: 45292 | B269: GraviTrax | C269: 26832 | D269: 0.2 | E269: =VLOOKUP(C269,Лист1!H:K,4,0) -> А | F269: =VLOOKUP(C269,Лист1!H:L,5,0) -> 2777.22 | G269: =IFERROR(VLOOKUP(CONCATENATE(C269,A269),Лист1!D:E,2,0),0) -> 0
A270: 45292 | B270: GraviTrax | C270: 27605 | D270: 0.2 | E270: =VLOOKUP(C270,Лист1!H:K,4,0) -> С | F270: =VLOOKUP(C270,Лист1!H:L,5,0) -> 388.32 | G270: =IFERROR(VLOOKUP(CONCATENATE(C270,A270),Лист1!D:E,2,0),0) -> 0
A271: 45292 | B271: GraviTrax | C271: 27607 | D271: 0.2 | E271: =VLOOKUP(C271,Лист1!H:K,4,0) -> ВИАТ | F271: =VLOOKUP(C271,Лист1!H:L,5,0) -> 388.32 | G271: =IFERROR(VLOOKUP(CONCATENATE(C271,A271),Лист1!D:E,2,0),0) -> 0
A272: 45292 | B272: GraviTrax | C272: 27609 | D272: 0.25 | E272: =VLOOKUP(C272,Лист1!H:K,4,0) -> С | F272: =VLOOKUP(C272,Лист1!H:L,5,0) -> 777.24 | G272: =IFERROR(VLOOKUP(CONCATENATE(C272,A272),Лист1!D:E,2,0),0) -> 0
A273: 45292 | B273: GraviTrax | C273: 27610 | D273: 0.25 | E273: =VLOOKUP(C273,Лист1!H:K,4,0) -> С | F273: =VLOOKUP(C273,Лист1!H:L,5,0) -> 777.24 | G273: =IFERROR(VLOOKUP(CONCATENATE(C273,A273),Лист1!D:E,2,0),0) -> 0
A274: 45292 | B274: Great Pretenders | C274: 10910 | D274: 0.2 | E274: =VLOOKUP(C274,Лист1!H:K,4,0) -> СТОК-ВИАТ | F274: =VLOOKUP(C274,Лист1!H:L,5,0) -> 193.86 | G274: =IFERROR(VLOOKUP(CONCATENATE(C274,A274),Лист1!D:E,2,0),0) -> 0
A275: 45292 | B275: Great Pretenders | C275: 10950 | D275: 0.2 | E275: =VLOOKUP(C275,Лист1!H:K,4,0) -> СТОК-ВИАТ | F275: =VLOOKUP(C275,Лист1!H:L,5,0) -> 82.8 | G275: =IFERROR(VLOOKUP(CONCATENATE(C275,A275),Лист1!D:E,2,0),0) -> 0
A276: 45292 | B276: Great Pretenders | C276: 11620 | D276: 0.2 | E276: =VLOOKUP(C276,Лист1!H:K,4,0) -> СТОК-ВИАТ | F276: =VLOOKUP(C276,Лист1!H:L,5,0) -> 193.86 | G276: =IFERROR(VLOOKUP(CONCATENATE(C276,A276),Лист1!D:E,2,0),0) -> 0
... A349: 45292 | B349: Great Pretenders | C349: 91210 | D349: 0.2 | E349: =VLOOKUP(C349,Лист1!H:K,4,0) -> ВИАТ | F349: =VLOOKUP(C349,Лист1!H:L,5,0) -> 238.32 | G349: =IFERROR(VLOOKUP(CONCATENATE(C349,A349),Лист1!D:E,2,0),0) -> 0
A350: 45292 | B350: Great Pretenders | C350: 17010GP | D350: 0.2 | E350: =VLOOKUP(C350,Лист1!H:K,4,0) -> СТОК-ВИАТ | F350: =VLOOKUP(C350,Лист1!H:L,5,0) -> 138.36 | G350: =IFERROR(VLOOKUP(CONCATENATE(C350,A350),Лист1!D:E,2,0),0) -> 0
A351: 45292 | B351: Great Pretenders | C351: 35303GP | D351: 0.2 | E351: =VLOOKUP(C351,Лист1!H:K,4,0) -> СТОК-ВИАТ | F351: =VLOOKUP(C351,Лист1!H:L,5,0) -> 277.2 | G351: =IFERROR(VLOOKUP(CONCATENATE(C351,A351),Лист1!D:E,2,0),0) -> 0
A352: 45292 | B352: Great Pretenders | C352: 35305GP | D352: 0.2 | E352: =VLOOKUP(C352,Лист1!H:K,4,0) -> СТОК-ВИАТ | F352: =VLOOKUP(C352,Лист1!H:L,5,0) -> 277.2 | G352: =IFERROR(VLOOKUP(CONCATENATE(C352,A352),Лист1!D:E,2,0),0) -> 0
A353: 45292 | B353: Great Pretenders | C353: 35307GP | D353: 0.2 | E353: =VLOOKUP(C353,Лист1!H:K,4,0) -> СТОК-ВИАТ | F353: =VLOOKUP(C353,Лист1!H:L,5,0) -> 277.2 | G353: =IFERROR(VLOOKUP(CONCATENATE(C353,A353),Лист1!D:E,2,0),0) -> 0
A354: 45292 | B354: Great Pretenders | C354: 90201GP | D354: 0.2 | E354: =VLOOKUP(C354,Лист1!H:K,4,0) -> СТОК-ВИАТ | F354: =VLOOKUP(C354,Лист1!H:L,5,0) -> 193.86 | G354: =IFERROR(VLOOKUP(CONCATENATE(C354,A354),Лист1!D:E,2,0),0) -> 0
A355: 45292 | B355: Great Pretenders | C355: 90205GP | D355: 0.2 | E355: =VLOOKUP(C355,Лист1!H:K,4,0) -> СТОК-ВИАТ | F355: =VLOOKUP(C355,Лист1!H:L,5,0) -> 221.64 | G355: =IFERROR(VLOOKUP(CONCATENATE(C355,A355),Лист1!D:E,2,0),0) -> 0
A356: 45292 | B356: Infantino | C356: 315092 | D356: 0.2 | E356: =VLOOKUP(C356,Лист1!H:K,4,0) -> В | F356: =VLOOKUP(C356,Лист1!H:L,5,0) -> 777.24 | G356: =IFERROR(VLOOKUP(CONCATENATE(C356,A356),Лист1!D:E,2,0),0) -> 0
A357: 45292 | B357: Infantino | C357: 315127 | D357: 0.2 | E357: =VLOOKUP(C357,Лист1!H:K,4,0) -> СТОК-ВИАТ | F357: =VLOOKUP(C357,Лист1!H:L,5,0) -> 499.44 | G357: =IFERROR(VLOOKUP(CONCATENATE(C357,A357),Лист1!D:E,2,0),0) -> 0
A358: 45292 | B358: Infantino | C358: 004373I | D358: 0.2 | E358: =VLOOKUP(C358,Лист1!H:K,4,0) -> СТОК-ВИАТ | F358: =VLOOKUP(C358,Лист1!H:L,5,0) -> 277.2 | G358: =IFERROR(VLOOKUP(CONCATENATE(C358,A358),Лист1!D:E,2,0),0) -> 0
A359: 45292 | B359: Infantino | C359: 004627I | D359: 0.2 | E359: =VLOOKUP(C359,Лист1!H:K,4,0) -> В | F359: =VLOOKUP(C359,Лист1!H:L,5,0) -> 777.24 | G359: =IFERROR(VLOOKUP(CONCATENATE(C359,A359),Лист1!D:E,2,0),0) -> 0
A360: 45292 | B360: Infantino | C360: 004854I | D360: 0.2 | E360: =VLOOKUP(C360,Лист1!H:K,4,0) -> СТОК-ВИАТ | F360: =VLOOKUP(C360,Лист1!H:L,5,0) -> 388.32 | G360: =IFERROR(VLOOKUP(CONCATENATE(C360,A360),Лист1!D:E,2,0),0) -> 0
A361: 45292 | B361: Infantino | C361: 004896I | D361: 0.2 | E361: =VLOOKUP(C361,Лист1!H:K,4,0) -> А | F361: =VLOOKUP(C361,Лист1!H:L,5,0) -> 1610.58 | G361: =IFERROR(VLOOKUP(CONCATENATE(C361,A361),Лист1!D:E,2,0),0) -> 0
A362: 45292 | B362: Infantino | C362: 004907I | D362: 0.2 | E362: =VLOOKUP(C362,Лист1!H:K,4,0) -> СТОК-ВИАТ | F362: =VLOOKUP(C362,Лист1!H:L,5,0) -> 277.2 | G362: =IFERROR(VLOOKUP(CONCATENATE(C362,A362),Лист1!D:E,2,0),0) -> 0
A363: 45292 | B363: Infantino | C363: 004909I | D363: 0.2 | E363: =VLOOKUP(C363,Лист1!H:K,4,0) -> В | F363: =VLOOKUP(C363,Лист1!H:L,5,0) -> 777.24 | G363: =IFERROR(VLOOKUP(CONCATENATE(C363,A363),Лист1!D:E,2,0),0) -> 0
A364: 45292 | B364: Infantino | C364: 004913I | D364: 0.2 | E364: =VLOOKUP(C364,Лист1!H:K,4,0) -> СТОК-ВИАТ | F364: =VLOOKUP(C364,Лист1!H:L,5,0) -> 388.32 | G364: =IFERROR(VLOOKUP(CONCATENATE(C364,A364),Лист1!D:E,2,0),0) -> 0
A365: 45292 | B365: Infantino | C365: 004914I | D365: 0.2 | E365: =VLOOKUP(C365,Лист1!H:K,4,0) -> А | F365: =VLOOKUP(C365,Лист1!H:L,5,0) -> 1610.58 | G365: =IFERROR(VLOOKUP(CONCATENATE(C365,A365),Лист1!D:E,2,0),0) -> 0
A366: 45292 | B366: Infantino | C366: 004915I | D366: 0.2 | E366: =VLOOKUP(C366,Лист1!H:K,4,0) -> А | F366: =VLOOKUP(C366,Лист1!H:L,5,0) -> 1610.58 | G366: =IFERROR(VLOOKUP(CONCATENATE(C366,A366),Лист1!D:E,2,0),0) -> 0
A367: 45292 | B367: Infantino | C367: 005053I | D367: 0.2 | E367: =VLOOKUP(C367,Лист1!H:K,4,0) -> СТОК-ВИАТ | F367: =VLOOKUP(C367,Лист1!H:L,5,0) -> 304.98 | G367: =IFERROR(VLOOKUP(CONCATENATE(C367,A367),Лист1!D:E,2,0),0) -> 0
A368: 45292 | B368: Infantino | C368: 005202I | D368: 0.2 | E368: =VLOOKUP(C368,Лист1!H:K,4,0) -> СТОК-ВИАТ | F368: =VLOOKUP(C368,Лист1!H:L,5,0) -> 388.32 | G368: =IFERROR(VLOOKUP(CONCATENATE(C368,A368),Лист1!D:E,2,0),0) -> 0
A369: 45292 | B369: Infantino | C369: 005232I | D369: 0.2 | E369: =VLOOKUP(C369,Лист1!H:K,4,0) -> СТОК-ВИАТ | F369: =VLOOKUP(C369,Лист1!H:L,5,0) -> 388.32 | G369: =IFERROR(VLOOKUP(CONCATENATE(C369,A369),Лист1!D:E,2,0),0) -> 0
... A401: 45292 | B401: JoyBand-Bontoy | C401: WB104 | D401: 0.3 | E401: =VLOOKUP(C401,Лист1!H:K,4,0) -> ВИАТ | F401: =VLOOKUP(C401,Лист1!H:L,5,0) -> 221.64 | G401: =IFERROR(VLOOKUP(CONCATENATE(C401,A401),Лист1!D:E,2,0),0) -> 0
A402: 45292 | B402: JoyBand-Purple cow | C402: 18 | D402: 0.15 | E402: =VLOOKUP(C402,Лист1!H:K,4,0) -> V | F402: =VLOOKUP(C402,Лист1!H:L,5,0) -> 154.98 | G402: =IFERROR(VLOOKUP(CONCATENATE(C402,A402),Лист1!D:E,2,0),0) -> 0
A403: 45292 | B403: JoyBand-Purple cow | C403: 61 | D403: 0.2 | E403: =VLOOKUP(C403,Лист1!H:K,4,0) -> V | F403: =VLOOKUP(C403,Лист1!H:L,5,0) -> 154.98 | G403: =IFERROR(VLOOKUP(CONCATENATE(C403,A403),Лист1!D:E,2,0),0) -> 0
A404: 45292 | B404: JoyBand-Purple cow | C404: 78 | D404: 0.2 | E404: =VLOOKUP(C404,Лист1!H:K,4,0) -> ВИАТ | F404: =VLOOKUP(C404,Лист1!H:L,5,0) -> 154.98 | G404: =IFERROR(VLOOKUP(CONCATENATE(C404,A404),Лист1!D:E,2,0),0) -> 0
A405: 45292 | B405: JoyBand-Purple cow | C405: 125 | D405: 0.2 | E405: =VLOOKUP(C405,Лист1!H:K,4,0) -> ВИАТ | F405: =VLOOKUP(C405,Лист1!H:L,5,0) -> 249.42 | G405: =IFERROR(VLOOKUP(CONCATENATE(C405,A405),Лист1!D:E,2,0),0) -> 0
A406: 45292 | B406: JoyBand-Purple cow | C406: 132 | D406: 0.2 | E406: =VLOOKUP(C406,Лист1!H:K,4,0) -> ВИАТ | F406: =VLOOKUP(C406,Лист1!H:L,5,0) -> 249.42 | G406: =IFERROR(VLOOKUP(CONCATENATE(C406,A406),Лист1!D:E,2,0),0) -> 0
A407: 45292 | B407: JoyBand-Purple cow | C407: 177 | D407: 0.15 | E407: =VLOOKUP(C407,Лист1!H:K,4,0) -> СТОК-ВИАТ | F407: =VLOOKUP(C407,Лист1!H:L,5,0) -> 443.88 | G407: =IFERROR(VLOOKUP(CONCATENATE(C407,A407),Лист1!D:E,2,0),0) -> 0
A408: 45292 | B408: JoyBand-Purple cow | C408: 184 | D408: 0.15 | E408: =VLOOKUP(C408,Лист1!H:K,4,0) -> СТОК-ВИАТ | F408: =VLOOKUP(C408,Лист1!H:L,5,0) -> 221.64 | G408: =IFERROR(VLOOKUP(CONCATENATE(C408,A408),Лист1!D:E,2,0),0) -> 0
A409: 45292 | B409: JoyBand-Purple cow | C409: 207 | D409: 0.15 | E409: =VLOOKUP(C409,Лист1!H:K,4,0) -> СТОК-ВИАТ | F409: =VLOOKUP(C409,Лист1!H:L,5,0) -> 443.88 | G409: =IFERROR(VLOOKUP(CONCATENATE(C409,A409),Лист1!D:E,2,0),0) -> 0
A410: 45292 | B410: JoyBand-Purple cow | C410: 353 | D410: 0.2 | E410: =VLOOKUP(C410,Лист1!H:K,4,0) -> СТОК-ВИАТ | F410: =VLOOKUP(C410,Лист1!H:L,5,0) -> 154.98 | G410: =IFERROR(VLOOKUP(CONCATENATE(C410,A410),Лист1!D:E,2,0),0) -> 0
A411: 45292 | B411: JoyBand-Purple cow | C411: 583 | D411: 0.15 | E411: =VLOOKUP(C411,Лист1!H:K,4,0) -> СТОК-ВИАТ | F411: =VLOOKUP(C411,Лист1!H:L,5,0) -> 154.98 | G411: =IFERROR(VLOOKUP(CONCATENATE(C411,A411),Лист1!D:E,2,0),0) -> 0
A412: 45292 | B412: JoyBand-Purple cow | C412: 681 | D412: 0.15 | E412: =VLOOKUP(C412,Лист1!H:K,4,0) -> СТОК-ВИАТ | F412: =VLOOKUP(C412,Лист1!H:L,5,0) -> 154.98 | G412: =IFERROR(VLOOKUP(CONCATENATE(C412,A412),Лист1!D:E,2,0),0) -> 0
A413: 45292 | B413: JoyBand-Purple cow | C413: 740 | D413: 0.2 | E413: =VLOOKUP(C413,Лист1!H:K,4,0) -> V | F413: =VLOOKUP(C413,Лист1!H:L,5,0) -> 154.98 | G413: =IFERROR(VLOOKUP(CONCATENATE(C413,A413),Лист1!D:E,2,0),0) -> 0
... A431: 45292 | B431: JoyBand-Trends | C431: 86800 | D431: 0.15 | E431: =VLOOKUP(C431,Лист1!H:K,4,0) -> СТОК-ВИАТ | F431: =VLOOKUP(C431,Лист1!H:L,5,0) -> 221.64 | G431: =IFERROR(VLOOKUP(CONCATENATE(C431,A431),Лист1!D:E,2,0),0) -> 0
A432: 45292 | B432: JoyBand-Trends | C432: 90200Т | D432: 0.25 | E432: =VLOOKUP(C432,Лист1!H:K,4,0) -> СТОК-ВИАТ | F432: =VLOOKUP(C432,Лист1!H:L,5,0) -> 221.64 | G432: =IFERROR(VLOOKUP(CONCATENATE(C432,A432),Лист1!D:E,2,0),0) -> 0
A433: 45292 | B433: Martinelia | C433: 11911 | D433: 0.2 | E433: =VLOOKUP(C433,Лист1!H:K,4,0) -> СТОК-ВИАТ | F433: =VLOOKUP(C433,Лист1!H:L,5,0) -> 321.66 | G433: =IFERROR(VLOOKUP(CONCATENATE(C433,A433),Лист1!D:E,2,0),0) -> 0
A434: 45292 | B434: Martinelia | C434: 11912 | D434: 0.2 | E434: =VLOOKUP(C434,Лист1!H:K,4,0) -> СТОК-ВИАТ | F434: =VLOOKUP(C434,Лист1!H:L,5,0) -> 388.32 | G434: =IFERROR(VLOOKUP(CONCATENATE(C434,A434),Лист1!D:E,2,0),0) -> 0
A435: 45292 | B435: Martinelia | C435: 11916 | D435: 0.2 | E435: =VLOOKUP(C435,Лист1!H:K,4,0) -> V | F435: =VLOOKUP(C435,Лист1!H:L,5,0) -> 499.44 | G435: =IFERROR(VLOOKUP(CONCATENATE(C435,A435),Лист1!D:E,2,0),0) -> 0
A436: 45292 | B436: Martinelia | C436: 11934 | D436: 0.2 | E436: =VLOOKUP(C436,Лист1!H:K,4,0) -> V | F436: =VLOOKUP(C436,Лист1!H:L,5,0) -> 443.88 | G436: =IFERROR(VLOOKUP(CONCATENATE(C436,A436),Лист1!D:E,2,0),0) -> 0
...

Sheet Лист1
A1: Номенклатура.Артикул | B1: Період, Місяць.Початок місяця | C1: Выручка | E1: Выручка
A2: 004627I | B2: 01.01.2025 | C2: 30 | D2: =CONCATENATE(A2,B2*1) -> 004627I45658 | E2: 30 | H2: 3361 | I2: 50 IQ завдань Динозаври | J2: шт | K2: СТОК-ВИАТ | L2: 166.14
A3: 004627I | B3: 01.02.2025 | C3: 27 | D3: =CONCATENATE(A3,B3*1) -> 004627I45689 | E3: 27 | H3: 378 | I3: 50 IQ завдань Єдинороги | J3: шт | K3: СТОК-ВИАТ | L3: 166.14
A4: 004627I | B4: 01.03.2025 | C4: 20 | D4: =CONCATENATE(A4,B4*1) -> 004627I45717 | E4: 20 | H4: 572609 | I4: Anne Geddes Лялька "Маленька Зебра", 31 см | J4: шт | K4: V | L4: 499.44
A5: 004627I | B5: 01.04.2025 | C5: 27 | D5: =CONCATENATE(A5,B5*1) -> 004627I45748 | E5: 27 | H5: 572611 | I5: Anne Geddes Лялька "Маленька Коала", 31 см | J5: шт | K5: V | L5: 499.44
A6: 004627I | B6: 01.05.2025 | C6: 15 | D6: =CONCATENATE(A6,B6*1) -> 004627I45778 | E6: 15 | H6: 21071AG | I6: Anne Geddes Лялька "Маленьке Ведмежатко" з сумкою та стікерами, 23 см | J6: шт | K6: V | L6: 388.32
A7: 004627I | B7: 01.06.2025 | C7: 27 | D7: =CONCATENATE(A7,B7*1) -> 004627I45809 | E7: 27 | H7: 572618 | I7: Anne Geddes Лялька "Маленьке Ведмежатко", 31 см | J7: шт | K7: V | L7: 555
A8: 004627I | B8: 01.07.2025 | C8: 17 | D8: =CONCATENATE(A8,B8*1) -> 004627I45839 | E8: 17 | H8: 21072 | I8: Anne Geddes Лялька "Маленьке Зайченя" з сумкою та стікерами, 23 см | J8: шт | K8: V | L8: 388.32
A9: 004627I | B9: 01.08.2025 | C9: 27 | D9: =CONCATENATE(A9,B9*1) -> 004627I45870 | E9: 27 | H9: 572620 | I9: Anne Geddes Лялька "Маленьке Зайченя", 31 см | J9: шт | K9: V | L9: 555
A10: 004627I | B10: 01.09.2025 | C10: 19 | D10: =CONCATENATE(A10,B10*1) -> 004627I45901 | E10: 19 | H10: 572610 | I10: Anne Geddes Лялька "Маленький Жирафик", 31 см | J10: шт | K10: V | L10: 499.44
A11: 004627I | B11: 01.10.2025 | C11: 21 | D11: =CONCATENATE(A11,B11*1) -> 004627I45931 | E11: 21 | H11: 575706 | I11: Anne Geddes Набір ляльок "Маленькі сестри Кошенятка", 38 см та 23см | J11: шт | K11: V | L11: 777.24
A12: 004627I | B12: 01.11.2025 | C12: 25 | D12: =CONCATENATE(A12,B12*1) -> 004627I45962 | E12: 25 | H12: 4003 | I12: Aqua Dragons - Набір DELUXUE | J12: шт | K12: СТОК-ВИАТ | L12: 77.22
A13: 004627I | B13: 01.12.2025 | C13: 64 | D13: =CONCATENATE(A13,B13*1) -> 004627I45992 | E13: 64 | H13: 4004 | I13: Aqua Dragons - Нове Життя | J13: шт | K13: СТОК-ВИАТ | L13: 32.76
A14: 004885I | B14: 01.03.2025 | C14: 1 | D14: =CONCATENATE(A14,B14*1) -> 004885I45717 | E14: 1 | H14: 4001 | I14: Aqua Dragons - Підводний світ | J14: шт | K14: СТОК-ВИАТ | L14: 60.54
A15: 004885I | B15: 01.07.2025 | C15: 2 | D15: =CONCATENATE(A15,B15*1) -> 004885I45839 | E15: 2 | H15: PAW22301 | I15: AquaSound Килимок для малювання на водній основі "Magiс aqua sounds PAW Patrol" | J15: шт | K15: ВИАТ | L15: 777.24
A16: 004885I | B16: 01.08.2025 | C16: 32 | D16: =CONCATENATE(A16,B16*1) -> 004885I45870 | E16: 32 | H16: 77021 | I16: Baby Secrets Ігровий набір з колискою | J16: шт | K16: СТОК-ВИАТ | L16: 110.58
A17: 004885I | B17: 01.09.2025 | C17: 39 | D17: =CONCATENATE(A17,B17*1) -> 004885I45901 | E17: 39 | H17: 77020 | I17: Baby Secrets Ігровий набір з коляскою | J17: шт | K17: СТОК-ВИАТ | L17: 55.02
A18: 004885I | B18: 01.10.2025 | C18: 61 | D18: =CONCATENATE(A18,B18*1) -> 004885I45931 | E18: 61 | H18: 77022 | I18: Baby Secrets Ігровий набір з коником-качалкою | J18: шт | K18: СТОК-ВИАТ | L18: 55.02
A19: 004885I | B19: 01.11.2025 | C19: 51 | D19: =CONCATENATE(A19,B19*1) -> 004885I45962 | E19: 51 | H19: 76922 | I19: Baby Secrets Ігровий набір з пупсиком (50 видів у асортименті) | J19: шт | K19: СТОК-ВИАТ | L19: 32.76
A20: 004885I | B20: 01.12.2025 | C20: 23 | D20: =CONCATENATE(A20,B20*1) -> 004885I45992 | E20: 23 | H20: 77023 | I20: Baby Secrets Ігровий набір зі стільчиком для годування | J20: шт | K20: СТОК-ВИАТ | L20: 110.58
A21: 004896I | B21: 01.01.2025 | C21: 64 | D21: =CONCATENATE(A21,B21*1) -> 004896I45658 | E21: 64 | H21: BHR17 | I21: Bad Habbit Rabbitz іграшка плюшева колекційна | J21: шт | K21: Новинка | L21: 277.2
A22: 004896I | B22: 01.02.2025 | C22: 37 | D22: =CONCATENATE(A22,B22*1) -> 004896I45689 | E22: 37 | H22: 113506 | I22: Baobab Набір 3в1 : Дитячим сповивальний столик з аксесуарами | J22: шт | K22: СТОК-ВИАТ | L22: 193.86
A23: 004896I | B23: 01.03.2025 | C23: 43 | D23: =CONCATENATE(A23,B23*1) -> 004896I45717 | E23: 43 | H23: 113504 | I23: Baobab Набір 4в1 : Пупсик Камілла BEBE VANILLE з дитячим сповивальним столиком і аксесуарами | J23: шт | K23: СТОК-ВИАТ | L23: 55.02
A24: 004896I | B24: 01.04.2025 | C24: 43 | D24: =CONCATENATE(A24,B24*1) -> 004896I45748 | E24: 43 | H24: 113503 | I24: Baobab Пупсик зі звуковими ефектами Камілла BEBE VANILLE | J24: шт | K24: СТОК-ВИАТ | L24: 143.88
A25: 004896I | B25: 01.05.2025 | C25: 44 | D25: =CONCATENATE(A25,B25*1) -> 004896I45778 | E25: 44 | H25: 113508 | I25: Baobab Пупсик інтерактивний Емма BEBE VANILLE | J25: шт | K25: СТОК-ВИАТ | L25: 55.02
A26: 004896I | B26: 01.06.2025 | C26: 35 | D26: =CONCATENATE(A26,B26*1) -> 004896I45809 | E26: 35 | H26: 113511 | I26: Baobab Пупсик інтерактивний Клара BEBE VANILLE з аксесуарами | J26: шт | K26: СТОК-ВИАТ | L26: 243.9
A27: 004896I | B27: 01.07.2025 | C27: 52 | D27: =CONCATENATE(A27,B27*1) -> 004896I45839 | E27: 52 | H27: 113500 | I27: Baobab Пупсик інтерактивний Марго BEBE VANILLE | J27: шт | K27: СТОК-ВИАТ | L27: 55.02
A28: 004896I | B28: 01.08.2025 | C28: 40 | D28: =CONCATENATE(A28,B28*1) -> 004896I45870 | E28: 40 | H28: 113502 | I28: Baobab Пупсик інтерактивний Хлоя BEBE VANILLE | J28: шт | K28: СТОК-ВИАТ | L28: 55.02
A29: 004896I | B29: 01.09.2025 | C29: 39 | D29: =CONCATENATE(A29,B29*1) -> 004896I45901 | E29: 39 | H29: 113505 | I29: Baobab Пупсик Камілла BEBE VANILLE з коляскою | J29: шт | K29: СТОК-ВИАТ | L29: 243.9
A30: 004896I | B30: 01.10.2025 | C30: 42 | D30: =CONCATENATE(A30,B30*1) -> 004896I45931 | E30: 42 | H30: 113507 | I30: Baobab Пупсик Камілла BEBE VANILLE зі стільчиком для годування | J30: шт | K30: СТОК-ВИАТ | L30: 55.02
A31: 004896I | B31: 01.11.2025 | C31: 40 | D31: =CONCATENATE(A31,B31*1) -> 004896I45962 | E31: 40 | H31: 961017 | I31: Besties 3D наліпки з блискітками "Зірка" (12 шт) | J31: шт | K31: С | L31: 38.34
A32: 004896I | B32: 01.12.2025 | C32: 28 | D32: =CONCATENATE(A32,B32*1) -> 004896I45992 | E32: 28 | H32: 961016 | I32: Besties 3D наліпки з блискітками "Серце" (12 шт) | J32: шт | K32: С | L32: 38.34
A33: 004909I | B33: 01.01.2025 | C33: 47 | D33: =CONCATENATE(A33,B33*1) -> 004909I45658 | E33: 47 | H33: 961040 | I33: Besties Арт-мозаїка "Зимова красуня"/ Бестіс Арт-мозаїка "Зимова красуня" | J33: шт | K33: С | L33: 55.02
... A71: 005053I | B71: 01.05.2025 | C71: 1 | D71: =CONCATENATE(A71,B71*1) -> 005053I45778 | E71: 1 | H71: 961037 | I71: Besties Стікербук за номерами «Summer»/ Бестіс Стікербук за номерами «Самер» | J71: шт | K71: С | L71: 66.12
A72: 5058 | B72: 01.01.2025 | C72: 15 | D72: =CONCATENATE(A72,B72*1) -> 505845658 | E72: 15 | H72: 961022 | I72: Besties Щоденник А5 з чарівною ручкою (50 аркушів, фіолетовий) | J72: шт | K72: В | L72: 154.98
A73: 5058 | B73: 01.02.2025 | C73: 22 | D73: =CONCATENATE(A73,B73*1) -> 505845689 | E73: 22 | H73: 961007 | I73: Besties Щоденник А5 з чарівною ручкою (50 аркушів) | J73: шт | K73: V | L73: 154.98
A74: 5058 | B74: 01.03.2025 | C74: 13 | D74: =CONCATENATE(A74,B74*1) -> 505845717 | E74: 13 | H74: 961021 | I74: Besties Щоденник А5 із замочком (60 аркушів) | J74: шт | K74: В | L74: 138.36
A75: 5058 | B75: 01.04.2025 | C75: 8 | D75: =CONCATENATE(A75,B75*1) -> 505845748 | E75: 8 | H75: 961044 | I75: Besties Щоденник із замочком "Зимовий секрет"/ Бестіс Щоденник із замочком "Зимовий секрет" | J75: шт | K75: С | L75: 138.36
A76: 5058 | B76: 01.05.2025 | C76: 6 | D76: =CONCATENATE(A76,B76*1) -> 505845778 | E76: 6 | H76: BL7014UK(UA) | I76: Blasta Набір BLASTA BOYS 6 фл. + 4 трафарети | J76: шт | K76: СТОК-ВИАТ | L76: 55.02
A77: 5058 | B77: 01.06.2025 | C77: 7 | D77: =CONCATENATE(A77,B77*1) -> 505845809 | E77: 7 | H77: BL7016UK(UA) | I77: Blasta Набір BLASTA GARAGE 12 фл. + 3 авто + гараж | J77: шт | K77: СТОК-ВИАТ | L77: 49.44
A78: 5058 | B78: 01.07.2025 | C78: 11 | D78: =CONCATENATE(A78,B78*1) -> 505845839 | E78: 11 | H78: BL7015UK(UA) | I78: Blasta Набір BLASTA GIRLS 6 фл. 4 трафарети | J78: шт | K78: СТОК-ВИАТ | L78: 10.56
A79: 5058 | B79: 01.08.2025 | C79: 15 | D79: =CONCATENATE(A79,B79*1) -> 505845870 | E79: 15 | H79: BL7017UK(UA) | I79: Blasta Набір BLASTA Делюкс магія 8 фл. + 8 трафаретів | J79: шт | K79: СТОК-ВИАТ | L79: 10.56
A80: 5058 | B80: 01.09.2025 | C80: 22 | D80: =CONCATENATE(A80,B80*1) -> 505845901 | E80: 22 | H80: BL7018UK(UA) | I80: Blasta Набір BLASTA Стартовий набір 4 фл. | J80: шт | K80: СТОК-ВИАТ | L80: 10.56
A81: 5058 | B81: 01.10.2025 | C81: 25 | D81: =CONCATENATE(A81,B81*1) -> 505845931 | E81: 25 | H81: MB3104UK(UA) | I81: Bleendy pens Mini набір №1 10 фл. + 5 розмальовок | J81: шт | K81: СТОК-ВИАТ | L81: 27.24
A82: 5058 | B82: 01.11.2025 | C82: 27 | D82: =CONCATENATE(A82,B82*1) -> 505845962 | E82: 27 | H82: MB3105UK(UA) | I82: Bleendy pens Mini набір №2 20 фл. | J82: шт | K82: СТОК-ВИАТ | L82: 10.56
A83: 5058 | B83: 01.12.2025 | C83: 34 | D83: =CONCATENATE(A83,B83*1) -> 505845992 | E83: 34 | H83: MB3106UK(UA) | I83: Bleendy pens Mini набір №3 20 фл. + 10 розмальовок + 10 трафаретів | J83: шт | K83: СТОК-ВИАТ | L83: 66.12
A84: 005059I | B84: 01.01.2025 | C84: 48 | D84: =CONCATENATE(A84,B84*1) -> 005059I45658 | E84: 48 | H84: BP1404UK(UA) | I84: Bleendy pens Набір BIG BOX 16 фл. + творча колекція | J84: шт | K84: СТОК-ВИАТ | L84: 10.56
A85: 005059I | B85: 01.02.2025 | C85: 39 | D85: =CONCATENATE(A85,B85*1) -> 005059I45689 | E85: 39 | H85: BP1232UK(UA) | I85: Bleendy pens Набір Fashion Дизайн 8 фл. + 3 ляльки + 32 аксесуари | J85: шт | K85: СТОК-ВИАТ | L85: 55.02
A86: 005059I | B86: 01.03.2025 | C86: 62 | D86: =CONCATENATE(A86,B86*1) -> 005059I45717 | E86: 62 | H86: BP2103UK(UA) | I86: Bleendy pens Набір Жива природа 4 фл. + 15 розмальовок | J86: шт | K86: СТОК-ВИАТ | L86: 21.66
A87: 005059I | B87: 01.04.2025 | C87: 35 | D87: =CONCATENATE(A87,B87*1) -> 005059I45748 | E87: 35 | H87: BP2105UK(UA) | I87: Bleendy pens Набір Жива природа 4 фл. + 15 розмальовок (new) | J87: шт | K87: СТОК-ВИАТ | L87: 10.56
A88: 005059I | B88: 01.05.2025 | C88: 31 | D88: =CONCATENATE(A88,B88*1) -> 005059I45778 | E88: 31 | H88: BP1010UK(UA) | I88: Bleendy pens Набір Казкові герої 6 фл. + 6 3Д моделі | J88: шт | K88: СТОК-ВИАТ | L88: 38.34
A89: 005059I | B89: 01.06.2025 | C89: 37 | D89: =CONCATENATE(A89,B89*1) -> 005059I45809 | E89: 37 | H89: BP1009UK(UA) | I89: Bleendy pens Набір Космічні прибульці 6 фл. + 6 3Д моделей | J89: шт | K89: СТОК-ВИАТ | L89: 10.56
A90: 005059I | B90: 01.07.2025 | C90: 35 | D90: =CONCATENATE(A90,B90*1) -> 005059I45839 | E90: 35 | H90: BP1008UK(UA) | I90: Bleendy pens Набір Кумедні тварини 6 фл. + 6 3Д моделей | J90: шт | K90: СТОК-ВИАТ | L90: 38.34
A91: 005059I | B91: 01.08.2025 | C91: 32 | D91: =CONCATENATE(A91,B91*1) -> 005059I45870 | E91: 32 | H91: BP1205UK(UA) | I91: Bleendy pens Набір Листівок 3Д 10 фл. + листівки + аксесуари | J91: шт | K91: СТОК-ВИАТ | L91: 77.22
A92: 005059I | B92: 01.09.2025 | C92: 35 | D92: =CONCATENATE(A92,B92*1) -> 005059I45901 | E92: 35 | H92: BP1233UK(UA) | I92: Bleendy pens Набір Оксамитові картинки 8 фл. + 8 картинок | J92: шт | K92: СТОК-ВИАТ | L92: 55.02
A93: 005059I | B93: 01.10.2025 | C93: 19 | D93: =CONCATENATE(A93,B93*1) -> 005059I45931 | E93: 19 | H93: BP1522UK(UA) | I93: Bleendy pens Набір Склади персонаж 8 фл + 1000 комбінацій | J93: шт | K93: СТОК-ВИАТ | L93: 10.56
A94: 005059I | B94: 01.11.2025 | C94: 26 | D94: =CONCATENATE(A94,B94*1) -> 005059I45962 | E94: 26 | H94: BP2104UK(UA) | I94: Bleendy pens Набір Фантазія 4 фл. + 15 розмальовок | J94: шт | K94: СТОК-ВИАТ | L94: 21.66
A95: 005059I | B95: 01.12.2025 | C95: 37 | D95: =CONCATENATE(A95,B95*1) -> 005059I45992 | E95: 37 | H95: BP2106UK(UA) | I95: Bleendy pens Набір Фантазія 4 фл. + 15 розмальовок (new) | J95: шт | K95: СТОК-ВИАТ | L95: 10.56
... A120: 005207S | B120: 01.05.2025 | C120: 1 | D120: =CONCATENATE(A120,B120*1) -> 005207S45778 | E120: 1 | H120: 2312004/12 | I120: Bubble Pops М’яка іграшка "Грейпфрутова кішка" | J120: шт | K120: V | L120: 388.32
A121: 5209 | B121: 01.01.2025 | C121: 168 | D121: =CONCATENATE(A121,B121*1) -> 520945658 | E121: 168 | H121: 2312004/9 | I121: Bubble Pops М’яка іграшка "Кавуневий аксолотль" | J121: шт | K121: V | L121: 388.32
A122: 5209 | B122: 01.02.2025 | C122: 90 | D122: =CONCATENATE(A122,B122*1) -> 520945689 | E122: 90 | H122: 2312004/3 | I122: Bubble Pops М’яка іграшка "Лимонне мишеня" | J122: шт | K122: V | L122: 388.32
A123: 5209 | B123: 01.03.2025 | C123: 74 | D123: =CONCATENATE(A123,B123*1) -> 520945717 | E123: 74 | H123: 2312004/7 | I123: Bubble Pops М’яка іграшка "М'ятна капібара" | J123: шт | K123: V | L123: 388.32
A124: 5209 | B124: 01.04.2025 | C124: 81 | D124: =CONCATENATE(A124,B124*1) -> 520945748 | E124: 81 | H124: 2312004/1 | I124: Bubble Pops М’яка іграшка "Малиновий Єдиноріг" | J124: шт | K124: V | L124: 388.32
A125: 5209 | B125: 01.05.2025 | C125: 66 | D125: =CONCATENATE(A125,B125*1) -> 520945778 | E125: 66 | H125: 2312004/4 | I125: Bubble Pops М’яка іграшка "Полуничне зайченя" | J125: шт | K125: V | L125: 388.32
A126: 5209 | B126: 01.06.2025 | C126: 44 | D126: =CONCATENATE(A126,B126*1) -> 520945809 | E126: 44 | H126: 2312004/8 | I126: Bubble Pops М’яка іграшка "Чорничне медвежа" | J126: шт | K126: V | L126: 388.32
A127: 5209 | B127: 01.07.2025 | C127: 98 | D127: =CONCATENATE(A127,B127*1) -> 520945839 | E127: 98 | H127: 2312004/2 | I127: Bubble Pops М’яка іграшка "Чорничне цуценя" | J127: шт | K127: V | L127: 388.32
A128: 5209 | B128: 01.08.2025 | C128: 123 | D128: =CONCATENATE(A128,B128*1) -> 520945870 | E128: 123 | H128: 2312004/11 | I128: Bubble Pops М’яка іграшка "Шоколадна капібара" | J128: шт | K128: V | L128: 388.32
A129: 5209 | B129: 01.09.2025 | C129: 88 | D129: =CONCATENATE(A129,B129*1) -> 520945901 | E129: 88 | H129: 2312004/6 | I129: Bubble Pops М’яка іграшка "Шоколадна мавпа" | J129: шт | K129: V | L129: 388.32
A130: 5209 | B130: 01.10.2025 | C130: 99 | D130: =CONCATENATE(A130,B130*1) -> 520945931 | E130: 99 | H130: 2402005/5 | I130: Bubble Pops М’яка іграшка міні "Виноградне кошеня" | J130: шт | K130: V | L130: 277.2
A131: 5209 | B131: 01.11.2025 | C131: 87 | D131: =CONCATENATE(A131,B131*1) -> 520945962 | E131: 87 | H131: 2402005/10 | I131: Bubble Pops М’яка іграшка міні "Вишнева корівка" | J131: шт | K131: V | L131: 277.2
A132: 5209 | B132: 01.12.2025 | C132: 204 | D132: =CONCATENATE(A132,B132*1) -> 520945992 | E132: 204 | H132: 2402005/12 | I132: Bubble Pops М’яка іграшка міні "Грейпфрутова кішка" | J132: шт | K132: V | L132: 277.2
A133: 005233I | B133: 01.02.2025 | C133: 1 | D133: =CONCATENATE(A133,B133*1) -> 005233I45689 | E133: 1 | H133: 2402005/9 | I133: Bubble Pops М’яка іграшка міні "Кавуневий аксолотль" | J133: шт | K133: V | L133: 277.2
A134: 005233I | B134: 01.03.2025 | C134: 2 | D134: =CONCATENATE(A134,B134*1) -> 005233I45717 | E134: 2 | H134: 2402005/3 | I134: Bubble Pops М’яка іграшка міні "Лимонне мишеня" | J134: шт | K134: V | L134: 277.2
A135: 005233I | B135: 01.04.2025 | C135: 1 | D135: =CONCATENATE(A135,B135*1) -> 005233I45748 | E135: 1 | H135: 2402005/7 | I135: Bubble Pops М’яка іграшка міні "М'ятна капібара" | J135: шт | K135: V | L135: 277.2
A136: 005233I | B136: 01.05.2025 | C136: 1 | D136: =CONCATENATE(A136,B136*1) -> 005233I45778 | E136: 1 | H136: 2402005/1 | I136: Bubble Pops М’яка іграшка міні "Малиновий Єдиноріг" | J136: шт | K136: V | L136: 277.2
A137: 005233I | B137: 01.06.2025 | C137: 3 | D137: =CONCATENATE(A137,B137*1) -> 005233I45809 | E137: 3 | H137: 2402005/4 | I137: Bubble Pops М’яка іграшка міні "Полуничне зайченя" | J137: шт | K137: V | L137: 277.2
A138: 005362I | B138: 01.01.2025 | C138: 162 | D138: =CONCATENATE(A138,B138*1) -> 005362I45658 | E138: 162 | H138: 2402005/8 | I138: Bubble Pops М’яка іграшка міні "Чорничне медвежа" | J138: шт | K138: V | L138: 277.2
A139: 005362I | B139: 01.02.2025 | C139: 130 | D139: =CONCATENATE(A139,B139*1) -> 005362I45689 | E139: 130 | H139: 2402005/2 | I139: Bubble Pops М’яка іграшка міні "Чорничне цуценя" | J139: шт | K139: V | L139: 277.2
A140: 005362I | B140: 01.03.2025 | C140: 135 | D140: =CONCATENATE(A140,B140*1) -> 005362I45717 | E140: 135 | H140: 2402005/11 | I140: Bubble Pops М’яка іграшка міні "Шоколадна капібара" | J140: шт | K140: V | L140: 277.2
A141: 005362I | B141: 01.04.2025 | C141: 146 | D141: =CONCATENATE(A141,B141*1) -> 005362I45748 | E141: 146 | H141: 2402005/6 | I141: Bubble Pops М’яка іграшка міні "Шоколадна мавпа" | J141: шт | K141: V | L141: 277.2
A142: 005362I | B142: 01.05.2025 | C142: 176 | D142: =CONCATENATE(A142,B142*1) -> 005362I45778 | E142: 176 | H142: 63855 | I142: Bullyland Soft Play Фігурка Бегемот | J142: шт | K142: СТОК-ВИАТ | L142: 243.9
A143: 005362I | B143: 01.06.2025 | C143: 147 | D143: =CONCATENATE(A143,B143*1) -> 005362I45809 | E143: 147 | H143: 63843 | I143: Bullyland Soft Play Фігурка Білка | J143: шт | K143: СТОК-ВИАТ | L143: 216.12
A144: 005362I | B144: 01.07.2025 | C144: 186 | D144: =CONCATENATE(A144,B144*1) -> 005362I45839 | E144: 186 | H144: 63897 | I144: Bullyland Soft Play Фігурка Єдиноріг | J144: шт | K144: СТОК-ВИАТ | L144: 355.02
A145: 005362I | B145: 01.08.2025 | C145: 179 | D145: =CONCATENATE(A145,B145*1) -> 005362I45870 | E145: 179 | H145: 63851 | I145: Bullyland Soft Play Фігурка Лев | J145: шт | K145: СТОК-ВИАТ | L145: 243.9
A146: 005362I | B146: 01.09.2025 | C146: 183 | D146: =CONCATENATE(A146,B146*1) -> 005362I45901 | E146: 183 | H146: 63854 | I146: Bullyland Soft Play Фігурка Слон | J146: шт | K146: СТОК-ВИАТ | L146: 366.12
A147: 005362I | B147: 01.10.2025 | C147: 171 | D147: =CONCATENATE(A147,B147*1) -> 005362I45931 | E147: 171 | H147: 63853 | I147: Bullyland Soft Play Фігурка Тигр | J147: шт | K147: СТОК-ВИАТ | L147: 243.9
A148: 005362I | B148: 01.11.2025 | C148: 227 | D148: =CONCATENATE(A148,B148*1) -> 005362I45962 | E148: 227 | H148: 67655 | I148: Bullyland Soft Play Фігурка Тюлень | J148: шт | K148: СТОК-ВИАТ | L148: 238.32
A149: 005362I | B149: 01.12.2025 | C149: 364 | D149: =CONCATENATE(A149,B149*1) -> 005362I45992 | E149: 364 | H149: 63865 | I149: Bullyland Soft Play Фігурка Черепаха | J149: шт | K149: СТОК-ВИАТ | L149: 299.46
A150: 5364 | B150: 01.03.2025 | C150: 3 | D150: =CONCATENATE(A150,B150*1) -> 536445717 | E150: 3 | H150: 13111 | I150: Bullyland WD "Гарний динозавр" Набір із 2 фігурок - Арло, Спот | J150: шт | K150: СТОК-ВИАТ | L150: 93.9
A151: 5364 | B151: 01.04.2025 | C151: 15 | D151: =CONCATENATE(A151,B151*1) -> 536445748 | E151: 15 | H151: 13181 | I151: Bullyland WD "Моана" Набір із 4 фігурок - Мауї, Моана, Хейхе, Какамора | J151: шт | K151: СТОК-ВИАТ | L151: 166.14
A152: 5364 | B152: 01.05.2025 | C152: 30 | D152: =CONCATENATE(A152,B152*1) -> 536445778 | E152: 30 | H152: 13427 | I152: Bullyland WD "Рапуецель" Набір із 4 фігурок - Рапунцель, Флін, Паскаль, Максимус | J152: шт | K152: СТОК-ВИАТ | L152: 166.14
A153: 5364 | B153: 01.06.2025 | C153: 27 | D153: =CONCATENATE(A153,B153*1) -> 536445809 | E153: 27 | H153: 12798 | I153: Bullyland WD "Тачки 3" Фігурка Блискавка МакКвін | J153: шт | K153: СТОК-ВИАТ | L153: 4.98
A154: 5364 | B154: 01.07.2025 | C154: 32 | D154: =CONCATENATE(A154,B154*1) -> 536445839 | E154: 32 | H154: 12909 | I154: Bullyland WD "Тачки 3" Фігурка Джексон Шторм | J154: шт | K154: СТОК-ВИАТ | L154: 4.98
A155: 5364 | B155: 01.08.2025 | C155: 37 | D155: =CONCATENATE(A155,B155*1) -> 536445870 | E155: 37 | H155: 12908 | I155: Bullyland WD "Тачки 3" Фігурка Крус Рамірес | J155: шт | K155: СТОК-ВИАТ | L155: 4.98
A156: 5364 | B156: 01.09.2025 | C156: 33 | D156: =CONCATENATE(A156,B156*1) -> 536445901 | E156: 33 | H156: 12799 | I156: Bullyland WD "Тачки 3" Фігурка Метр | J156: шт | K156: СТОК-ВИАТ | L156: 38.34
A157: 5364 | B157: 01.10.2025 | C157: 29 | D157: =CONCATENATE(A157,B157*1) -> 536445931 | E157: 29 | H157: 12910 | I157: Bullyland WD "Тачки 3" Фігурка Міс Крихітка | J157: шт | K157: СТОК-ВИАТ | L157: 4.98
A158: 5364 | B158: 01.11.2025 | C158: 31 | D158: =CONCATENATE(A158,B158*1) -> 536445962 | E158: 31 | H158: 12216 | I158: Bullyland WD "Холодне серце" Набір із 5 фігурок - Анна, Ельза, Свен, Крістоф, Олаф | J158: шт | K158: СТОК-ВИАТ | L158: 232.8
A159: 5364 | B159: 01.12.2025 | C159: 48 | D159: =CONCATENATE(A159,B159*1) -> 536445992 | E159: 48 | H159: 12941 | I159: Bullyland WD "Холодні пригоди Олафа" Анна | J159: шт | K159: СТОК-ВИАТ | L159: 4.98
A160: 5373 | B160: 01.01.2025 | C160: 21 | D160: =CONCATENATE(A160,B160*1) -> 537345658 | E160: 21 | H160: 12940 | I160: Bullyland WD "Холодні пригоди Олафа" Фігурка Ельза | J160: шт | K160: СТОК-ВИАТ | L160: 4.98
A161: 5373 | B161: 01.02.2025 | C161: 23 | D161: =CONCATENATE(A161,B161*1) -> 537345689 | E161: 23 | H161: 12943 | I161: Bullyland WD "Холодні пригоди Олафа" Фігурка Олаф із гірляндою | J161: шт | K161: СТОК-ВИАТ | L161: 4.98
...
